GameBoy1/GameBoy_RTL_Qsys_submit/debug_tests/PPU3.sv
`timescale 1ns / 1ns

//Authors: Nicolas Alarcon, Claire Cizdziel, Donovan Sproule

/* WARNING: DOES NOT HAVE INTERRUPTS OR ANY EXTERNAL OUTPUTS IMPLEMENTED */

module PPU3
(
    input logic clk,
    input logic rst,
    
    /* System access for PPU internal registers */
    input logic [15:0] ADDR,
    input logic WR,
    input logic RD,
    input logic [7:0] MMIO_DATA_out,
    output logic [7:0] MMIO_DATA_in,
    
    /* Interrupts */
    output logic IRQ_V_BLANK,
    output logic IRQ_LCDC,
    
    output logic [1:0] PPU_MODE,
    
    /* VRAM access for PPU */
    output logic PPU_RD,
    output logic [15:0] PPU_ADDR,
    input logic [7:0] PPU_DATA_in,
    
    output logic [1:0] PX_OUT,
    output logic PX_valid
);

`define OAM_BASE_ADDR 16'hFE00
`define OAM_END_ADDR 16'hFE9F
`define NO_BOOT 0

`define PPU_ADDR_INC(x) PPU_ADDR <= PPU_ADDR + x;

logic sprite_in_range;
logic [7:0] LY, x_pos;  // x-pos in range [0, 159]
logic [15:0] current_offset;
logic [3:0] sprites_loaded;
logic sprite_found;

logic [8:0] cycles;

logic [7:0] sprite_y_buff [9:0];
logic [7:0] sprite_x_buff [9:0];
logic [7:0] sprite_offset_buff [9:0]; 		// stores start of sprite entries in OAM (entry + 2 => for tile no.)

logic sprite_shift_go;
logic sprite_shift_load;
logic [1:0] sprite_shift_output;
logic [7:0] sprite_tile_row [1:0];

PPU_SHIFT_REG sprite_fifo(.clk(clk), .rst(rst), .data(sprite_tile_row), .go(sprite_shift_go), .load(sprite_shift_load), .q(sprite_shift_output));

logic bg_shift_go;
logic bg_shift_load;
logic [1:0] bg_shift_output;
logic [7:0] bg_tile_row [1:0];

PPU_SHIFT_REG bg_fifo(.clk(clk), .rst(rst), .data(bg_tile_row), .go(bg_shift_go), .load(bg_shift_load), .q(bg_shift_output));

typedef enum bit [1:0] {H_BLANK, V_BLANK, SCAN, DRAW} PPU_STATES_t;

/* External registers */
logic [7:0] LCDC, STAT, SCX, SCY, LYC, DMA, BGP, OBP0, OBP1, WX, WY; // Register alias

logic [7:0] FF40;
assign LCDC = FF40;

logic [7:0] FF41;
assign STAT = FF41;

logic [7:0] FF42;
assign SCY = FF42;

logic [7:0] FF43;
assign SCX = FF43;

logic [7:0] FF44;

logic [7:0] FF45;
assign LYC = FF45;

logic [7:0] FF46;
assign DMA = FF46;

logic [7:0] FF47;
assign BGP = FF47;

logic [7:0] FF48; 
assign OBP0 = {FF48[7:2], 2'b00}; // Last 2 bits are not used

logic [7:0] FF49;
assign OBP1 = {FF49[7:2], 2'b00};

logic [7:0] FF4A;
assign WY = FF4A;

logic [7:0] FF4B;
assign WX = FF4B;

/* Register Assignment
 * 
 * 	if a register memory address is being indexed it gets updated here 
 *  -- As a warning the following may introduce timing oddities compared to other group
 */
always_ff @(posedge clk)
begin
    if (rst)
    begin
        FF40 <= `NO_BOOT ? 8'h91 : 0;
        FF41 <= 0;
        FF42 <= 0;
        FF43 <= 0;
        FF45 <= 0;
        FF46 <= 0;
        FF47 <= `NO_BOOT ? 8'hFC : 0;
        FF48 <= `NO_BOOT ? 8'hFF : 0;
        FF49 <= `NO_BOOT ? 8'hFF : 0;
        FF4A <= 0; 
        FF4B <= 0;  
    end
    else
    begin
        FF40 <= (WR && (ADDR == 16'hFF40)) ? MMIO_DATA_out : FF40;
	    FF41 <= (WR && (ADDR == 16'hFF41)) ? {MMIO_DATA_out[7:3], FF41[2:0]} : {FF41[7:3], LYC == LY, PPU_MODE};
	    FF42 <= (WR && (ADDR == 16'hFF42)) ? MMIO_DATA_out : FF42;
	    FF43 <= (WR && (ADDR == 16'hFF43)) ? MMIO_DATA_out : FF43;
	    FF45 <= (WR && (ADDR == 16'hFF45)) ? MMIO_DATA_out : FF45;
	    FF46 <= (WR && (ADDR == 16'hFF46)) ? MMIO_DATA_out : FF46;
	    FF47 <= (WR && (ADDR == 16'hFF47)) ? MMIO_DATA_out : FF47;
	    FF48 <= (WR && (ADDR == 16'hFF48)) ? MMIO_DATA_out : FF48;
	    FF49 <= (WR && (ADDR == 16'hFF49)) ? MMIO_DATA_out : FF49;
	    FF4A <= (WR && (ADDR == 16'hFF4A)) ? MMIO_DATA_out : FF4A;
	    FF4B <= (WR && (ADDR == 16'hFF4B)) ? MMIO_DATA_out : FF4B;
    end
end

/* 
 * If we detect a memory request we return back the current
 * state of the register
 */ 
always_comb	// doesn't wait for a posedge clk
begin
    case (ADDR)
        16'hFF40: MMIO_DATA_in = FF40;
        16'hFF41: MMIO_DATA_in = {1'b1, FF41[6:0]};
        16'hFF42: MMIO_DATA_in = FF42;
        16'hFF43: MMIO_DATA_in = FF43;
        16'hFF44: MMIO_DATA_in = FF44;
        16'hFF45: MMIO_DATA_in = FF45;
        16'hFF46: MMIO_DATA_in = FF46;
        16'hFF47: MMIO_DATA_in = FF47;
        16'hFF48: MMIO_DATA_in = FF48;
        16'hFF49: MMIO_DATA_in = FF49;
        16'hFF4A: MMIO_DATA_in = FF4A;
        16'hFF4B: MMIO_DATA_in = FF4B;
        default : MMIO_DATA_in = 8'hFF;
    endcase
end

/* -- State Switching machine -- */
always_ff @(posedge clk) begin
    if (rst) begin
			x_pos <= 0;
			cycles <= 1;
			LY <= 0;
			PPU_ADDR <= `OAM_BASE_ADDR;
			PPU_MODE <= SCAN;
    end else if (LCDC[7]) begin
    	cycles <= cycles + 1;
		/* -- Following block happens on a per scanline basis (456 cycles per line) -- */
        case (PPU_MODE)
            SCAN: begin
		    	if (PPU_ADDR > `OAM_END_ADDR) 
					PPU_MODE <= DRAW;
				if (LY >= 144)
					PPU_MODE <= V_BLANK;
			end
		    DRAW: 
		    	LY <= LY;
		    	// if x_pos is off-screen switch to H_blank
		    H_BLANK: 
		    	if (cycles >= 455) begin		// we reached the end of the scanline
					LY <= LY + 1;
					x_pos <= 0;
					PPU_MODE <= SCAN;
					cycles <= 0;
				end
		    V_BLANK: 							// not technically necessary but here for completeness
				PPU_MODE <= H_BLANK;
        endcase
    end
end

assign sprite_in_range = ((LY + 16 >= PPU_DATA_in) &&
							(LY + 16 < PPU_DATA_in + (8 << LCDC[2])));
assign current_offset = PPU_ADDR - `OAM_BASE_ADDR;

/* -- OAM Scan State Machine -- */
always_ff @(posedge clk) begin
	if (rst || PPU_MODE == H_BLANK) begin
		sprites_loaded <= 0;
		sprite_found <= 0;
	end else if (PPU_MODE == SCAN) begin
		if (!cycles[0])	begin								// forces alternating clock cycles
			if (sprite_in_range && sprites_loaded < 10) begin
				sprites_loaded <= sprites_loaded + 1;
				sprite_y_buff[sprites_loaded] <= PPU_DATA_in;
				sprite_offset_buff[sprites_loaded] <= current_offset[7:0];
				sprite_found <= 1;
				`PPU_ADDR_INC(1);							// jumps to x-byte
			end else `PPU_ADDR_INC(4);						// jumps to next sprite in OAM
		end else begin
			if (sprite_found) begin
				sprite_x_buff[sprites_loaded - 1] <= PPU_DATA_in;
				`PPU_ADDR_INC(3);						// jumps to next sprite in OAM
			end
			sprite_found <= 0;
		end

	end
end 

/* BG Draw Machine */
always_ff @(posedge clk) begin
	// sprite-staging mode:
	// 	1 - if sprite-x is in range grab it
	// 	2 - pause bg-staging
	// 	3 - fetches sprite tile from buffer 
	// 	4 - same as 2 & 3 in bg-stage mode
	//
	// bg-staging mode:
	// 	1 - grabs the current tile (use x-pos as an offset
	// 		from the base)
	//	2 - grabs the corresponding row of byte from the tile
	//		saved
	//	3 - grabs the next row so that our color can be
	//		encoded
	//	4 - decode and push the row into the FIFO
	//
	// drawing mode:
	// 	1 - apply the bg fifo mask for SCX
	// 	2 - grab pixel and do mixing
	// 	3 - push to LCD
	// 	4 - increment x-pos	
	// 	5 - check if we've hit the window
	//
	// if x-pos == 160 then move to h-blank
end
        
endmodule
    
module PPU_SHIFT_REG
(
    input clk,
    input rst,
    input logic [7:0] data [1:0],
    input logic go,
    input logic load,
    output logic [1:0] q
);

logic [7:0] shift_reg [0:1];

always_ff @(posedge clk)
begin
    if (rst)
    begin
        shift_reg[0] <= 0;
        shift_reg[1] <= 0;
    end
    else if (load)
    begin
        shift_reg[0] <= data[0];
        shift_reg[1] <= data[1];
    end
    else
    begin
        if (go)
        begin
            shift_reg[0][7:1] <= shift_reg[0][6:0];
            shift_reg[0][0] <= 0;
            shift_reg[1][7:1] <= shift_reg[1][6:0];
            shift_reg[1][0] <= 0;
        end
    end
end

assign q = {shift_reg[1][7], shift_reg[0][7]};
        
endmodule

GameBoy1/GameBoy_RTL_Qsys_submit/debug_tests/obj_dir/ppu3.vcd
$version Generated by VerilatedVcd $end
$date Wed Apr 17 22:06:37 2024
 $end
$timescale   1ns $end

 $scope module TOP $end
  $var wire 16 -% ADDR [15:0] $end
  $var wire  1 ]% IRQ_LCDC $end
  $var wire  1 U% IRQ_V_BLANK $end
  $var wire  8 M% MMIO_DATA_in [7:0] $end
  $var wire  8 E% MMIO_DATA_out [7:0] $end
  $var wire 16 u% PPU_ADDR [15:0] $end
  $var wire  8 }% PPU_DATA_in [7:0] $end
  $var wire  2 e% PPU_MODE [1:0] $end
  $var wire  1 m% PPU_RD $end
  $var wire  2 '& PX_OUT [1:0] $end
  $var wire  1 /& PX_valid $end
  $var wire  1 =% RD $end
  $var wire  1 5% WR $end
  $var wire  1 {$ clk $end
  $var wire  1 %% rst $end
  $scope module PPU3 $end
   $var wire 16 -% ADDR [15:0] $end
   $var wire  8 #$ BGP [7:0] $end
   $var wire  8 y# DMA [7:0] $end
   $var wire  8 Q# FF40 [7:0] $end
   $var wire  8 Y# FF41 [7:0] $end
   $var wire  8 i# FF42 [7:0] $end
   $var wire  8 a# FF43 [7:0] $end
   $var wire  8 )' FF44 [7:0] $end
   $var wire  8 q# FF45 [7:0] $end
   $var wire  8 y# FF46 [7:0] $end
   $var wire  8 #$ FF47 [7:0] $end
   $var wire  8 K$ FF48 [7:0] $end
   $var wire  8 S$ FF49 [7:0] $end
   $var wire  8 C$ FF4A [7:0] $end
   $var wire  8 ;$ FF4B [7:0] $end
   $var wire  1 ]% IRQ_LCDC $end
   $var wire  1 U% IRQ_V_BLANK $end
   $var wire  8 Q# LCDC [7:0] $end
   $var wire  8 C LY [7:0] $end
   $var wire  8 q# LYC [7:0] $end
   $var wire  8 M% MMIO_DATA_in [7:0] $end
   $var wire  8 E% MMIO_DATA_out [7:0] $end
   $var wire  8 +$ OBP0 [7:0] $end
   $var wire  8 3$ OBP1 [7:0] $end
   $var wire 16 u% PPU_ADDR [15:0] $end
   $var wire  8 }% PPU_DATA_in [7:0] $end
   $var wire  2 e% PPU_MODE [1:0] $end
   $var wire  1 m% PPU_RD $end
   $var wire  2 '& PX_OUT [1:0] $end
   $var wire  1 /& PX_valid $end
   $var wire  1 =% RD $end
   $var wire  8 a# SCX [7:0] $end
   $var wire  8 i# SCY [7:0] $end
   $var wire  8 Y# STAT [7:0] $end
   $var wire  1 5% WR $end
   $var wire  8 ;$ WX [7:0] $end
   $var wire  8 C$ WY [7:0] $end
   $var wire  1 g& bg_shift_go $end
   $var wire  1 o& bg_shift_load $end
   $var wire  2 I# bg_shift_output [1:0] $end
   $var wire  8 w& bg_tile_row(0) [7:0] $end
   $var wire  8 x& bg_tile_row(1) [7:0] $end
   $var wire  1 {$ clk $end
   $var wire 16 ?& current_offset [15:0] $end
   $var wire  9 c cycles [8:0] $end
   $var wire  1 %% rst $end
   $var wire  1 [ sprite_found $end
   $var wire  1 7& sprite_in_range $end
   $var wire  8 O" sprite_offset_buff(0) [7:0] $end
   $var wire  8 P" sprite_offset_buff(1) [7:0] $end
   $var wire  8 Q" sprite_offset_buff(2) [7:0] $end
   $var wire  8 R" sprite_offset_buff(3) [7:0] $end
   $var wire  8 S" sprite_offset_buff(4) [7:0] $end
   $var wire  8 T" sprite_offset_buff(5) [7:0] $end
   $var wire  8 U" sprite_offset_buff(6) [7:0] $end
   $var wire  8 V" sprite_offset_buff(7) [7:0] $end
   $var wire  8 W" sprite_offset_buff(8) [7:0] $end
   $var wire  8 X" sprite_offset_buff(9) [7:0] $end
   $var wire  1 G& sprite_shift_go $end
   $var wire  1 O& sprite_shift_load $end
   $var wire  2 A# sprite_shift_output [1:0] $end
   $var wire  8 W& sprite_tile_row(0) [7:0] $end
   $var wire  8 X& sprite_tile_row(1) [7:0] $end
   $var wire  8 ]! sprite_x_buff(0) [7:0] $end
   $var wire  8 ^! sprite_x_buff(1) [7:0] $end
   $var wire  8 _! sprite_x_buff(2) [7:0] $end
   $var wire  8 `! sprite_x_buff(3) [7:0] $end
   $var wire  8 a! sprite_x_buff(4) [7:0] $end
   $var wire  8 b! sprite_x_buff(5) [7:0] $end
   $var wire  8 c! sprite_x_buff(6) [7:0] $end
   $var wire  8 d! sprite_x_buff(7) [7:0] $end
   $var wire  8 e! sprite_x_buff(8) [7:0] $end
   $var wire  8 f! sprite_x_buff(9) [7:0] $end
   $var wire  8 k sprite_y_buff(0) [7:0] $end
   $var wire  8 l sprite_y_buff(1) [7:0] $end
   $var wire  8 m sprite_y_buff(2) [7:0] $end
   $var wire  8 n sprite_y_buff(3) [7:0] $end
   $var wire  8 o sprite_y_buff(4) [7:0] $end
   $var wire  8 p sprite_y_buff(5) [7:0] $end
   $var wire  8 q sprite_y_buff(6) [7:0] $end
   $var wire  8 r sprite_y_buff(7) [7:0] $end
   $var wire  8 s sprite_y_buff(8) [7:0] $end
   $var wire  8 t sprite_y_buff(9) [7:0] $end
   $var wire  4 S sprites_loaded [3:0] $end
   $var wire  8 K x_pos [7:0] $end
   $scope module bg_fifo $end
    $var wire  1 {$ clk $end
    $var wire  8 3 data(0) [7:0] $end
    $var wire  8 4 data(1) [7:0] $end
    $var wire  1 g& go $end
    $var wire  1 o& load $end
    $var wire  2 I# q [1:0] $end
    $var wire  1 %% rst $end
    $var wire  8 k$ shift_reg(0) [7:0] $end
    $var wire  8 l$ shift_reg(1) [7:0] $end
   $upscope $end
   $scope module sprite_fifo $end
    $var wire  1 {$ clk $end
    $var wire  8 # data(0) [7:0] $end
    $var wire  8 $ data(1) [7:0] $end
    $var wire  1 G& go $end
    $var wire  1 O& load $end
    $var wire  2 A# q [1:0] $end
    $var wire  1 %% rst $end
    $var wire  8 [$ shift_reg(0) [7:0] $end
    $var wire  8 \$ shift_reg(1) [7:0] $end
   $upscope $end
  $upscope $end
 $upscope $end
$enddefinitions $end


#0
b00000000 #
b00000000 $
b00000000 3
b00000000 4
b00000000 C
b00000000 K
b0000 S
0[
b000000000 c
b00000000 k
b00000000 l
b00000000 m
b00000000 n
b00000000 o
b00000000 p
b00000000 q
b00000000 r
b00000000 s
b00000000 t
b00000000 ]!
b00000000 ^!
b00000000 _!
b00000000 `!
b00000000 a!
b00000000 b!
b00000000 c!
b00000000 d!
b00000000 e!
b00000000 f!
b00000000 O"
b00000000 P"
b00000000 Q"
b00000000 R"
b00000000 S"
b00000000 T"
b00000000 U"
b00000000 V"
b00000000 W"
b00000000 X"
b00 A#
b00 I#
b00000000 Q#
b00000000 Y#
b00000000 a#
b00000000 i#
b00000000 q#
b00000000 y#
b00000000 #$
b00000000 +$
b00000000 3$
b00000000 ;$
b00000000 C$
b00000000 K$
b00000000 S$
b00000000 [$
b00000000 \$
b00000000 k$
b00000000 l$
0{$
0%%
b1111111101000000 -%
15%
0=%
b11111111 E%
b00000000 M%
0U%
0]%
b00 e%
0m%
b0000000000000000 u%
b00000000 }%
b00 '&
0/&
07&
b0000001000000000 ?&
0G&
0O&
b00000000 W&
b00000000 X&
0g&
0o&
b00000000 w&
b00000000 x&
b00000000 )'
#10
b11111111 Q#
b00000100 Y#
1{$
b11111111 M%
#20
0{$
#30
b000000001 c
b00000000 Q#
b00000000 Y#
1{$
1%%
b00000000 M%
b10 e%
b1111111000000000 u%
b0000000000000000 ?&
#40
0{$
0%%
#50
b11111111 Q#
b00000110 Y#
1{$
b11111111 M%
b01010000 }%
#60
0{$
b00000000 }%
#70
b000000010 c
1{$
b00011110 }%
#80
0{$
b00000000 }%
#90
b0001 S
1[
b000000011 c
b00000101 k
1{$
b1111111000000001 u%
b00000101 }%
17&
b0000000000000001 ?&
#100
0{$
b00000000 }%
07&
#110
0[
b000000100 c
b00000101 ]!
1{$
b1111111000000100 u%
b00000101 }%
17&
b0000000000000100 ?&
#120
0{$
b00000000 }%
07&
#130
b000000101 c
1{$
b1111111000001000 u%
b0000000000001000 ?&
#140
0{$
#150
b000000110 c
1{$
#160
0{$
#170
b000000111 c
1{$
b1111111000001100 u%
b0000000000001100 ?&
#180
0{$
#190
b000001000 c
1{$
#200
0{$
#210
b000001001 c
1{$
b1111111000010000 u%
b0000000000010000 ?&
#220
0{$
#230
b000001010 c
1{$
#240
0{$
#250
b000001011 c
1{$
b1111111000010100 u%
b0000000000010100 ?&
#260
0{$
#270
b000001100 c
1{$
#280
0{$
#290
b000001101 c
1{$
b1111111000011000 u%
b0000000000011000 ?&
#300
0{$
#310
b000001110 c
1{$
#320
0{$
#330
b000001111 c
1{$
b1111111000011100 u%
b0000000000011100 ?&
#340
0{$
#350
b000010000 c
1{$
#360
0{$
#370
b000010001 c
1{$
b1111111000100000 u%
b0000000000100000 ?&
#380
0{$
#390
b000010010 c
1{$
#400
0{$
#410
b000010011 c
1{$
b1111111000100100 u%
b0000000000100100 ?&
#420
0{$
#430
b000010100 c
1{$
#440
0{$
#450
b000010101 c
1{$
b1111111000101000 u%
b0000000000101000 ?&
#460
0{$
#470
b000010110 c
1{$
#480
0{$
#490
b000010111 c
1{$
b1111111000101100 u%
b0000000000101100 ?&
#500
0{$
#510
b000011000 c
1{$
#520
0{$
#530
b000011001 c
1{$
b1111111000110000 u%
b0000000000110000 ?&
#540
0{$
#550
b000011010 c
1{$
#560
0{$
#570
b000011011 c
1{$
b1111111000110100 u%
b0000000000110100 ?&
#580
0{$
#590
b000011100 c
1{$
#600
0{$
#610
b000011101 c
1{$
b1111111000111000 u%
b0000000000111000 ?&
#620
0{$
#630
b000011110 c
1{$
#640
0{$
#650
b000011111 c
1{$
b1111111000111100 u%
b0000000000111100 ?&
#660
0{$
#670
b000100000 c
1{$
#680
0{$
#690
b000100001 c
1{$
b1111111001000000 u%
b0000000001000000 ?&
#700
0{$
#710
b000100010 c
1{$
#720
0{$
#730
b000100011 c
1{$
b1111111001000100 u%
b0000000001000100 ?&
#740
0{$
#750
b000100100 c
1{$
#760
0{$
#770
b000100101 c
1{$
b1111111001001000 u%
b0000000001001000 ?&
#780
0{$
#790
b000100110 c
1{$
#800
0{$
#810
b000100111 c
1{$
b1111111001001100 u%
b0000000001001100 ?&
#820
0{$
#830
b000101000 c
1{$
#840
0{$
#850
b000101001 c
1{$
b1111111001010000 u%
b0000000001010000 ?&
#860
0{$
#870
b000101010 c
1{$
#880
0{$
#890
b000101011 c
1{$
b1111111001010100 u%
b0000000001010100 ?&
#900
0{$
#910
b000101100 c
1{$
#920
0{$
#930
b000101101 c
1{$
b1111111001011000 u%
b0000000001011000 ?&
#940
0{$
#950
b000101110 c
1{$
#960
0{$
#970
b000101111 c
1{$
b1111111001011100 u%
b0000000001011100 ?&
#980
0{$
#990
b000110000 c
1{$
#1000
0{$
#1010
b000110001 c
1{$
b1111111001100000 u%
b0000000001100000 ?&
#1020
0{$
#1030
b000110010 c
1{$
#1040
0{$
#1050
b000110011 c
1{$
b1111111001100100 u%
b0000000001100100 ?&
#1060
0{$
#1070
b000110100 c
1{$
#1080
0{$
#1090
b000110101 c
1{$
b1111111001101000 u%
b0000000001101000 ?&
#1100
0{$
#1110
b000110110 c
1{$
#1120
0{$
#1130
b000110111 c
1{$
b1111111001101100 u%
b0000000001101100 ?&
#1140
0{$
#1150
b000111000 c
1{$
#1160
0{$
#1170
b000111001 c
1{$
b1111111001110000 u%
b0000000001110000 ?&
#1180
0{$
#1190
b000111010 c
1{$
#1200
0{$
#1210
b000111011 c
1{$
b1111111001110100 u%
b0000000001110100 ?&
#1220
0{$
#1230
b000111100 c
1{$
#1240
0{$
#1250
b000111101 c
1{$
b1111111001111000 u%
b0000000001111000 ?&
#1260
0{$
#1270
b000111110 c
1{$
#1280
0{$
#1290
b000111111 c
1{$
b1111111001111100 u%
b0000000001111100 ?&
#1300
0{$
#1310
b001000000 c
1{$
#1320
0{$
#1330
b001000001 c
1{$
b1111111010000000 u%
b0000000010000000 ?&
#1340
0{$
#1350
b001000010 c
1{$
#1360
0{$
#1370
b001000011 c
1{$
b1111111010000100 u%
b0000000010000100 ?&
#1380
0{$
#1390
b001000100 c
1{$
#1400
0{$
#1410
b001000101 c
1{$
b1111111010001000 u%
b0000000010001000 ?&
#1420
0{$
#1430
b001000110 c
1{$
#1440
0{$
#1450
b001000111 c
1{$
b1111111010001100 u%
b0000000010001100 ?&
#1460
0{$
#1470
b001001000 c
1{$
#1480
0{$
#1490
b001001001 c
1{$
b1111111010010000 u%
b0000000010010000 ?&
#1500
0{$
#1510
b001001010 c
1{$
#1520
0{$
#1530
b001001011 c
1{$
b1111111010010100 u%
b0000000010010100 ?&
#1540
0{$
#1550
b001001100 c
1{$
#1560
0{$
#1570
b001001101 c
1{$
b1111111010011000 u%
b0000000010011000 ?&
#1580
0{$
#1590
b001001110 c
1{$
#1600
0{$
#1610
b001001111 c
1{$
b1111111010011100 u%
b0000000010011100 ?&
#1620
0{$
#1630
b001010000 c
1{$
#1640
0{$
#1650
b001010001 c
1{$
b1111111010100000 u%
b0000000010100000 ?&
#1660
0{$
#1670
b001010010 c
1{$
b11 e%
#1680
0{$
#1690
b001010011 c
b00000111 Y#
1{$
#1700
0{$
#1710
b001010100 c
1{$
#1720
0{$
#1730
b001010101 c
1{$
#1740
0{$
#1750
b001010110 c
1{$
#1760
0{$
#1770
b001010111 c
1{$
#1780
0{$
#1790
b001011000 c
1{$
#1800
0{$
#1810
b001011001 c
1{$
#1820
0{$
#1830
b001011010 c
1{$
#1840
0{$
#1850
b001011011 c
1{$
#1860
0{$
#1870
b001011100 c
1{$
#1880
0{$
#1890
b001011101 c
1{$
#1900
0{$
#1910
b001011110 c
1{$
#1920
0{$
#1930
b001011111 c
1{$
#1940
0{$
#1950
b001100000 c
1{$
#1960
0{$
#1970
b001100001 c
1{$
#1980
0{$
#1990
b001100010 c
1{$
#2000
0{$
#2010
b001100011 c
1{$
#2020
0{$
#2030
b001100100 c
1{$
#2040
0{$
#2050
b001100101 c
1{$
#2060
0{$
#2070
b001100110 c
1{$
#2080
0{$
#2090
b001100111 c
1{$
#2100
0{$
#2110
b001101000 c
1{$
#2120
0{$
#2130
b001101001 c
1{$
#2140
0{$
#2150
b001101010 c
1{$
#2160
0{$
#2170
b001101011 c
1{$
#2180
0{$
#2190
b001101100 c
1{$
#2200
0{$
#2210
b001101101 c
1{$
#2220
0{$
#2230
b001101110 c
1{$
#2240
0{$
#2250
b001101111 c
1{$
#2260
0{$
#2270
b001110000 c
1{$
#2280
0{$
#2290
b001110001 c
1{$
#2300
0{$
#2310
b001110010 c
1{$
#2320
0{$
#2330
b001110011 c
1{$
#2340
0{$
#2350
b001110100 c
1{$
#2360
0{$
#2370
b001110101 c
1{$
#2380
0{$
#2390
b001110110 c
1{$
#2400
0{$
#2410
b001110111 c
1{$
#2420
0{$
#2430
b001111000 c
1{$
#2440
0{$
#2450
b001111001 c
1{$
#2460
0{$
#2470
b001111010 c
1{$
#2480
0{$
#2490
b001111011 c
1{$
#2500
0{$
#2510
b001111100 c
1{$
#2520
0{$
#2530
b001111101 c
1{$
#2540
0{$
#2550
b001111110 c
1{$
#2560
0{$
#2570
b001111111 c
1{$
#2580
0{$
#2590
b010000000 c
1{$
#2600
0{$
#2610
b010000001 c
1{$
#2620
0{$
#2630
b010000010 c
1{$
#2640
0{$
#2650
b010000011 c
1{$
#2660
0{$
#2670
b010000100 c
1{$
#2680
0{$
#2690
b010000101 c
1{$
#2700
0{$
#2710
b010000110 c
1{$
#2720
0{$
#2730
b010000111 c
1{$
#2740
0{$
#2750
b010001000 c
1{$
#2760
0{$
#2770
b010001001 c
1{$
#2780
0{$
#2790
b010001010 c
1{$
#2800
0{$
#2810
b010001011 c
1{$
#2820
0{$
#2830
b010001100 c
1{$
#2840
0{$
#2850
b010001101 c
1{$
#2860
0{$
#2870
b010001110 c
1{$
#2880
0{$
#2890
b010001111 c
1{$
#2900
0{$
#2910
b010010000 c
1{$
#2920
0{$
#2930
b010010001 c
1{$
#2940
0{$
#2950
b010010010 c
1{$
#2960
0{$
#2970
b010010011 c
1{$
#2980
0{$
#2990
b010010100 c
1{$
#3000
0{$
#3010
b010010101 c
1{$
#3020
0{$
#3030
b010010110 c
1{$
#3040
0{$
#3050
b010010111 c
1{$
#3060
0{$
#3070
b010011000 c
1{$
#3080
0{$
#3090
b010011001 c
1{$
#3100
0{$
#3110
b010011010 c
1{$
#3120
0{$
#3130
b010011011 c
1{$
#3140
0{$
#3150
b010011100 c
1{$
#3160
0{$
#3170
b010011101 c
1{$
#3180
0{$
#3190
b010011110 c
1{$
#3200
0{$
#3210
b010011111 c
1{$
#3220
0{$
#3230
b010100000 c
1{$
#3240
0{$
#3250
b010100001 c
1{$
#3260
0{$
#3270
b010100010 c
1{$
#3280
0{$
#3290
b010100011 c
1{$
#3300
0{$
#3310
b010100100 c
1{$
#3320
0{$
#3330
b010100101 c
1{$
#3340
0{$
#3350
b010100110 c
1{$
#3360
0{$
#3370
b010100111 c
1{$
#3380
0{$
#3390
b010101000 c
1{$
#3400
0{$
#3410
b010101001 c
1{$
#3420
0{$
#3430
b010101010 c
1{$
#3440
0{$
#3450
b010101011 c
1{$
#3460
0{$
#3470
b010101100 c
1{$
#3480
0{$
#3490
b010101101 c
1{$
#3500
0{$
#3510
b010101110 c
1{$
#3520
0{$
#3530
b010101111 c
1{$
#3540
0{$
#3550
b010110000 c
1{$
#3560
0{$
#3570
b010110001 c
1{$
#3580
0{$
#3590
b010110010 c
1{$
#3600
0{$
#3610
b010110011 c
1{$
#3620
0{$
#3630
b010110100 c
1{$
#3640
0{$
#3650
b010110101 c
1{$
#3660
0{$
#3670
b010110110 c
1{$
#3680
0{$
#3690
b010110111 c
1{$
#3700
0{$
#3710
b010111000 c
1{$
#3720
0{$
#3730
b010111001 c
1{$
#3740
0{$
#3750
b010111010 c
1{$
#3760
0{$
#3770
b010111011 c
1{$
#3780
0{$
#3790
b010111100 c
1{$
#3800
0{$
#3810
b010111101 c
1{$
#3820
0{$
#3830
b010111110 c
1{$
#3840
0{$
#3850
b010111111 c
1{$
#3860
0{$
#3870
b011000000 c
1{$
#3880
0{$
#3890
b011000001 c
1{$
#3900
0{$
#3910
b011000010 c
1{$
#3920
0{$
#3930
b011000011 c
1{$
#3940
0{$
#3950
b011000100 c
1{$
#3960
0{$
#3970
b011000101 c
1{$
#3980
0{$
#3990
b011000110 c
1{$
#4000
0{$
#4010
b011000111 c
1{$
#4020
0{$
#4030
b011001000 c
1{$
#4040
0{$
#4050
b011001001 c
1{$
#4060
0{$
#4070
b011001010 c
1{$
#4080
0{$
#4090
b011001011 c
1{$
#4100
0{$
#4110
b011001100 c
1{$
#4120
0{$
#4130
b011001101 c
1{$
#4140
0{$
#4150
b011001110 c
1{$
#4160
0{$
#4170
b011001111 c
1{$
#4180
0{$
#4190
b011010000 c
1{$
#4200
0{$
#4210
b011010001 c
1{$
#4220
0{$
#4230
b011010010 c
1{$
#4240
0{$
#4250
b011010011 c
1{$
#4260
0{$
#4270
b011010100 c
1{$
#4280
0{$
#4290
b011010101 c
1{$
#4300
0{$
#4310
b011010110 c
1{$
#4320
0{$
#4330
b011010111 c
1{$
#4340
0{$
#4350
b011011000 c
1{$
#4360
0{$
#4370
b011011001 c
1{$
#4380
0{$
#4390
b011011010 c
1{$
#4400
0{$
#4410
b011011011 c
1{$
#4420
0{$
#4430
b011011100 c
1{$
#4440
0{$
#4450
b011011101 c
1{$
#4460
0{$
#4470
b011011110 c
1{$
#4480
0{$
#4490
b011011111 c
1{$
#4500
0{$
#4510
b011100000 c
1{$
#4520
0{$
#4530
b011100001 c
1{$
#4540
0{$
#4550
b011100010 c
1{$
#4560
0{$
#4570
b011100011 c
1{$
#4580
0{$
#4590
b011100100 c
1{$
#4600
0{$
#4610
b011100101 c
1{$
#4620
0{$
#4630
b011100110 c
1{$
#4640
0{$
#4650
b011100111 c
1{$
#4660
0{$
#4670
b011101000 c
1{$
#4680
0{$
#4690
b011101001 c
1{$
#4700
0{$
#4710
b011101010 c
1{$
#4720
0{$
#4730
b011101011 c
1{$
#4740
0{$
#4750
b011101100 c
1{$
#4760
0{$
#4770
b011101101 c
1{$
#4780
0{$
#4790
b011101110 c
1{$
#4800
0{$
#4810
b011101111 c
1{$
#4820
0{$
#4830
b011110000 c
1{$
#4840
0{$
#4850
b011110001 c
1{$
#4860
0{$
#4870
b011110010 c
1{$
#4880
0{$
#4890
b011110011 c
1{$
#4900
0{$
#4910
b011110100 c
1{$
#4920
0{$
#4930
b011110101 c
1{$
#4940
0{$
#4950
b011110110 c
1{$
#4960
0{$
#4970
b011110111 c
1{$
#4980
0{$
#4990
b011111000 c
1{$
#5000
0{$
#5010
b011111001 c
1{$
#5020
0{$
#5030
b011111010 c
1{$
#5040
0{$
#5050
b011111011 c
1{$
#5060
0{$
#5070
b011111100 c
1{$
#5080
0{$
#5090
b011111101 c
1{$
#5100
0{$
#5110
b011111110 c
1{$
#5120
0{$
#5130
b011111111 c
1{$
#5140
0{$
#5150
b100000000 c
1{$
#5160
0{$
#5170
b100000001 c
1{$
#5180
0{$
#5190
b100000010 c
1{$
#5200
0{$
#5210
b100000011 c
1{$
#5220
0{$
#5230
b100000100 c
1{$
#5240
0{$
#5250
b100000101 c
1{$
